DDLab5_2017/exercise_tb/ripple_adder_16bit.v
`timescale 1ns / 1ps

module full_adder(sum, cout, a, b, cin);

//data type declaration
input a, b, cin;
output sum, cout;
// behavior description

wire x,y,z;
xor i1(x,a,b);
xor i2(sum,x,cin);
and i3(y,x,cin);
and i4(z,a,b);
or i5(cout,y,z);

endmodule

module _16bit_adder_structural(sum, cout, a, b, cin);

//data type declaration
output [15:0]sum;
output cout;
input [15:0]a, b;
input cin;
// behavior description

full_adder fa0(.sum(sum[0]),.cout(c0),.a(a[0]),.b(b[0]),.cin(cin));
full_adder fa1(.sum(sum[1]),.cout(c1),.a(a[1]),.b(b[1]),.cin(c0));
full_adder fa2(.sum(sum[2]),.cout(c2),.a(a[2]),.b(b[2]),.cin(c1));
full_adder fa3(.sum(sum[3]),.cout(c3),.a(a[3]),.b(b[3]),.cin(c2));
full_adder fa4(.sum(sum[4]),.cout(c4),.a(a[4]),.b(b[4]),.cin(c3));
full_adder fa5(.sum(sum[5]),.cout(c5),.a(a[5]),.b(b[5]),.cin(c4));
full_adder fa6(.sum(sum[6]),.cout(c6),.a(a[6]),.b(b[6]),.cin(c5));
full_adder fa7(.sum(sum[7]),.cout(c7),.a(a[7]),.b(b[7]),.cin(c6));
full_adder fa8(.sum(sum[8]),.cout(c8),.a(a[8]),.b(b[8]),.cin(c7));
full_adder fa9(.sum(sum[9]),.cout(c9),.a(a[9]),.b(b[9]),.cin(c8));
full_adder fa10(.sum(sum[10]),.cout(c10),.a(a[10]),.b(b[10]),.cin(c9));
full_adder fa11(.sum(sum[11]),.cout(c11),.a(a[11]),.b(b[11]),.cin(c10));
full_adder fa12(.sum(sum[12]),.cout(c12),.a(a[12]),.b(b[12]),.cin(c11));
full_adder fa13(.sum(sum[13]),.cout(c13),.a(a[13]),.b(b[13]),.cin(c12));
full_adder fa14(.sum(sum[14]),.cout(c14),.a(a[14]),.b(b[14]),.cin(c13));
full_adder fa15(.sum(sum[15]),.cout(cout),.a(a[15]),.b(b[15]),.cin(c14));

endmodule

DDLab5_2017/exercise_tb/tb_16bit_structural.v
`timescale 1ns / 1ps

module fulladder_test;

//data type declaration

reg [15:0] a, b;
reg cin;
wire [15:0] sum;
wire cout;
_16bit_adder_structural DUT(sum, cout, a, b, cin);

// behavior description



initial
begin
	
	$dumpfile("16bit_RCA_structural.vcd"); //繪製波形檔
	$dumpvars;

	a = 16'b1111111100000000;
	b = 16'b1111111111111111;
	cin = 1'b1;
end

always #1
begin
a = ( a << 1 | cin );
$monitor("%4dns monitor: = a=%d b=%d cin=%d sum=%d cout=%d",$stime, a, b, cin, sum, cout);
end

always #2 b = b >> 2;
always #3 cin = ~cin ;
initial #15 $finish;

endmodule

DDLab5_2017/exercise_tb/16bit_RCA_structural.vcd
$date
	Sun Apr  9 22:49:51 2017
$end
$version
	Icarus Verilog
$end
$timescale
	1ps
$end
$scope module fulladder_test $end
$var wire 16 ! sum [15:0] $end
$var wire 1 " cout $end
$var reg 16 # a [15:0] $end
$var reg 16 $ b [15:0] $end
$var reg 1 % cin $end
$scope module DUT $end
$var wire 16 & a [15:0] $end
$var wire 16 ' b [15:0] $end
$var wire 1 % cin $end
$var wire 16 ( sum [15:0] $end
$var wire 1 " cout $end
$var wire 1 ) c9 $end
$var wire 1 * c8 $end
$var wire 1 + c7 $end
$var wire 1 , c6 $end
$var wire 1 - c5 $end
$var wire 1 . c4 $end
$var wire 1 / c3 $end
$var wire 1 0 c2 $end
$var wire 1 1 c14 $end
$var wire 1 2 c13 $end
$var wire 1 3 c12 $end
$var wire 1 4 c11 $end
$var wire 1 5 c10 $end
$var wire 1 6 c1 $end
$var wire 1 7 c0 $end
$scope module fa0 $end
$var wire 1 8 a $end
$var wire 1 9 b $end
$var wire 1 % cin $end
$var wire 1 7 cout $end
$var wire 1 : sum $end
$var wire 1 ; x $end
$var wire 1 < y $end
$var wire 1 = z $end
$upscope $end
$scope module fa1 $end
$var wire 1 > a $end
$var wire 1 ? b $end
$var wire 1 7 cin $end
$var wire 1 6 cout $end
$var wire 1 @ sum $end
$var wire 1 A x $end
$var wire 1 B y $end
$var wire 1 C z $end
$upscope $end
$scope module fa10 $end
$var wire 1 D a $end
$var wire 1 E b $end
$var wire 1 5 cout $end
$var wire 1 F sum $end
$var wire 1 G x $end
$var wire 1 H y $end
$var wire 1 I z $end
$var wire 1 ) cin $end
$upscope $end
$scope module fa11 $end
$var wire 1 J a $end
$var wire 1 K b $end
$var wire 1 5 cin $end
$var wire 1 4 cout $end
$var wire 1 L sum $end
$var wire 1 M x $end
$var wire 1 N y $end
$var wire 1 O z $end
$upscope $end
$scope module fa12 $end
$var wire 1 P a $end
$var wire 1 Q b $end
$var wire 1 4 cin $end
$var wire 1 3 cout $end
$var wire 1 R sum $end
$var wire 1 S x $end
$var wire 1 T y $end
$var wire 1 U z $end
$upscope $end
$scope module fa13 $end
$var wire 1 V a $end
$var wire 1 W b $end
$var wire 1 3 cin $end
$var wire 1 2 cout $end
$var wire 1 X sum $end
$var wire 1 Y x $end
$var wire 1 Z y $end
$var wire 1 [ z $end
$upscope $end
$scope module fa14 $end
$var wire 1 \ a $end
$var wire 1 ] b $end
$var wire 1 2 cin $end
$var wire 1 1 cout $end
$var wire 1 ^ sum $end
$var wire 1 _ x $end
$var wire 1 ` y $end
$var wire 1 a z $end
$upscope $end
$scope module fa15 $end
$var wire 1 b a $end
$var wire 1 c b $end
$var wire 1 1 cin $end
$var wire 1 " cout $end
$var wire 1 d sum $end
$var wire 1 e x $end
$var wire 1 f y $end
$var wire 1 g z $end
$upscope $end
$scope module fa2 $end
$var wire 1 h a $end
$var wire 1 i b $end
$var wire 1 6 cin $end
$var wire 1 0 cout $end
$var wire 1 j sum $end
$var wire 1 k x $end
$var wire 1 l y $end
$var wire 1 m z $end
$upscope $end
$scope module fa3 $end
$var wire 1 n a $end
$var wire 1 o b $end
$var wire 1 0 cin $end
$var wire 1 / cout $end
$var wire 1 p sum $end
$var wire 1 q x $end
$var wire 1 r y $end
$var wire 1 s z $end
$upscope $end
$scope module fa4 $end
$var wire 1 t a $end
$var wire 1 u b $end
$var wire 1 / cin $end
$var wire 1 . cout $end
$var wire 1 v sum $end
$var wire 1 w x $end
$var wire 1 x y $end
$var wire 1 y z $end
$upscope $end
$scope module fa5 $end
$var wire 1 z a $end
$var wire 1 { b $end
$var wire 1 . cin $end
$var wire 1 - cout $end
$var wire 1 | sum $end
$var wire 1 } x $end
$var wire 1 ~ y $end
$var wire 1 !" z $end
$upscope $end
$scope module fa6 $end
$var wire 1 "" a $end
$var wire 1 #" b $end
$var wire 1 - cin $end
$var wire 1 , cout $end
$var wire 1 $" sum $end
$var wire 1 %" x $end
$var wire 1 &" y $end
$var wire 1 '" z $end
$upscope $end
$scope module fa7 $end
$var wire 1 (" a $end
$var wire 1 )" b $end
$var wire 1 , cin $end
$var wire 1 + cout $end
$var wire 1 *" sum $end
$var wire 1 +" x $end
$var wire 1 ," y $end
$var wire 1 -" z $end
$upscope $end
$scope module fa8 $end
$var wire 1 ." a $end
$var wire 1 /" b $end
$var wire 1 + cin $end
$var wire 1 * cout $end
$var wire 1 0" sum $end
$var wire 1 1" x $end
$var wire 1 2" y $end
$var wire 1 3" z $end
$upscope $end
$scope module fa9 $end
$var wire 1 4" a $end
$var wire 1 5" b $end
$var wire 1 * cin $end
$var wire 1 ) cout $end
$var wire 1 6" sum $end
$var wire 1 7" x $end
$var wire 1 8" y $end
$var wire 1 9" z $end
$upscope $end
$upscope $end
$upscope $end
$enddefinitions $end
#0
$dumpvars
19"
08"
07"
16"
15"
14"
13"
02"
01"
10"
1/"
1."
0-"
1,"
1+"
0*"
1)"
0("
0'"
1&"
1%"
0$"
1#"
0""
0!"
1~
1}
0|
1{
0z
0y
1x
1w
0v
1u
0t
0s
1r
1q
0p
1o
0n
0m
1l
1k
0j
1i
0h
1g
0f
0e
1d
1c
1b
1a
0`
0_
1^
1]
1\
1[
0Z
0Y
1X
1W
1V
1U
0T
0S
1R
1Q
1P
1O
0N
0M
1L
1K
1J
1I
0H
0G
1F
1E
1D
0C
1B
1A
0@
1?
0>
0=
1<
1;
0:
19
08
17
16
15
14
13
12
11
10
1/
1.
1-
1,
1+
1*
1)
b1111111100000000 (
b1111111111111111 '
b1111111100000000 &
1%
b1111111111111111 $
b1111111100000000 #
1"
b1111111100000000 !
$end
#1000
16"
1:
0<
b1111111000000001 !
b1111111000000001 (
00"
12"
1*
0;
1=
11"
03"
18
0."
b1111111000000001 #
b1111111000000001 &
#2000
1F
1@
0B
06"
18"
1)
0^
1`
11
b11110000000011 !
b11110000000011 (
0d
1f
1"
0A
1C
17"
09"
1_
0a
1e
0g
1>
04"
0]
0c
b1111110000000011 #
b1111110000000011 &
b11111111111111 $
b11111111111111 '
#3000
0@
1L
07
1j
0l
0F
1H
15
1;
0=
0k
1m
1G
0I
08
1h
0D
b11100000000101 !
b11100000000101 (
1:
b1111100000000110 #
b1111100000000110 &
0%
#4000
1"
0d
1f
11
0j
0^
1`
1@
06
1p
0r
0L
1N
14
0R
1T
13
b1011 !
b1011 (
0X
1Z
12
1A
0C
0q
1s
1M
0O
1S
0U
1Y
0[
0>
1n
0J
0Q
0W
b1111000000001100 #
b1111000000001100 &
b111111111111 $
b111111111111 '
#5000
0"
1d
0f
01
1^
0`
02
1X
0Z
0p
03
1j
00
1v
0x
b1111000000010111 !
b1111000000010111 (
1R
0T
1k
0m
0w
1y
0S
0h
1t
0P
b1110000000011000 #
b1110000000011000 &
#6000
1r
10
0R
0j
1l
1v
05
04
16
0p
1/
1|
0~
0X
1F
0H
0L
0N
0@
1B
0;
1=
1q
0s
0}
1!"
0Y
0G
0M
17
18
0n
1z
0V
0E
0K
b1100010000110001 !
b1100010000110001 (
1:
0<
b1100000000110001 #
b1100000000110001 &
b1111111111 $
b1111111111 '
1%
#7000
1|
1@
0B
0v
1x
1.
1$"
0&"
b1000010001100011 !
b1000010001100011 (
0^
0A
1C
1w
0y
0%"
1'"
0_
1>
0t
1""
0\
b1000000001100011 #
b1000000001100011 &
#8000
0F
1$"
0*
0)
1j
0l
0|
1~
1-
1*"
0,"
0d
10"
02"
b111000111 !
b111000111 (
06"
08"
0k
1m
1}
0!"
0+"
1-"
0e
01"
07"
1h
0z
1("
0b
0/"
05"
b11000111 #
b11000111 &
b11111111 $
b11111111 '
#9000
16"
0@
1*"
1*
07
1p
0r
0$"
1&"
1,
00"
12"
1;
0=
0q
1s
1%"
0'"
11"
08
1n
0""
1."
b1010001101 !
b1010001101 (
1:
b110001110 #
b110001110 &
0%
#10000
0F
0*"
0*
0j
0)
0,
10"
02"
1@
06
1v
0x
16"
08"
b1101011011 !
b1101011011 (
1$"
0&"
0+
1A
0C
0w
1y
17"
0%"
0-"
0>
1t
0("
14"
0#"
0)"
b1100011100 #
b1100011100 &
b111111 $
b111111 '
#11000
0p
1j
00
1|
0~
00"
b11001110111 !
b11001110111 (
1F
1k
0m
0}
1!"
01"
1G
0h
1z
0."
1D
b11000111000 #
b11000111000 &
#12000
1*"
1r
1,
10
0$"
1&"
0j
1l
16
0p
1/
06"
1L
0v
1x
1.
0|
1~
1-
0@
1B
0;
1=
1q
0s
1%"
07"
1M
1w
0y
1}
0!"
17
18
0n
1""
04"
1J
0u
0{
b110010000001 !
b110010000001 (
1:
0<
b110001110001 #
b110001110001 &
b1111 $
b1111 '
1%
#13000
0,
1$"
0&"
0-
1|
0~
00"
0.
0+
1@
0B
1v
0x
1*"
0,"
0F
b1100011110011 !
b1100011110011 (
1R
0A
1C
0w
1+"
0G
1S
1>
0t
1("
0D
1P
b1100011100011 #
b1100011100011 &
#14000
0v
0/
0|
10"
0L
1X
b11000111001011 !
b11000111001011 (
1p
0r
0}
11"
0M
1Y
0q
1h
0z
1."
0J
1V
0i
0o
b11000111000111 #
b11000111000111 &
b11 $
b11 '
#15000
1v
0@
1/
07
0p
1r
0$"
16"
0R
1^
1;
0=
1q
0%"
17"
0S
1_
08
1n
0""
14"
0P
1\
b110001110010001 !
b110001110010001 (
1:
b110001110001110 #
b110001110001110 &
0%
