DDLab5_2017/LAB5_ex1/continuous_adder_16bit.v
`timescale 1ns / 1ps

module _16bit_adder_continuous (sum, cout, a, b, cin);

//port declaration

input [15:0] a, b;
input cin;
output [15:0] sum;
output cout;

// behavior description

assign {cout,sum} = a+ b +cin;

endmodule

DDLab5_2017/LAB5_ex1/tb_16bit_continuous.v
`timescale 1ns / 1ps

module fulladder_test;

//data type declaration

reg [15:0] a, b;
reg cin;
wire [15:0] sum;
wire cout;
_16bit_adder_continuous DUT(sum, cout, a, b, cin);

// behavior description



initial
begin
	
	$dumpfile("16bit_adder_continuous.vcd"); //繪製波形檔
	$dumpvars;

	a = 16'b1111111100000000;
	b = 16'b1111111111111111;
	cin = 1'b1;
end

always #1
begin
a = ( a << 1 | cin );
$monitor("%4dns monitor: = a=%d b=%d cin=%d sum=%d cout=%d",$stime, a, b, cin, sum, cout);
end

always #2 b = b >> 2;
always #3 cin = ~cin ;
initial #15 $finish;

endmodule

DDLab5_2017/LAB5_ex1/16bit_adder_continuous.vcd
$date
	Sun Apr  9 22:27:01 2017
$end
$version
	Icarus Verilog
$end
$timescale
	1ps
$end
$scope module fulladder_test $end
$var wire 16 ! sum [15:0] $end
$var wire 1 " cout $end
$var reg 16 # a [15:0] $end
$var reg 16 $ b [15:0] $end
$var reg 1 % cin $end
$scope module DUT $end
$var wire 16 & a [15:0] $end
$var wire 16 ' b [15:0] $end
$var wire 1 % cin $end
$var wire 16 ( sum [15:0] $end
$var wire 1 " cout $end
$upscope $end
$upscope $end
$enddefinitions $end
#0
$dumpvars
b1111111100000000 (
b1111111111111111 '
b1111111100000000 &
1%
b1111111111111111 $
b1111111100000000 #
1"
b1111111100000000 !
$end
#1000
b1111111000000001 !
b1111111000000001 (
b1111111000000001 #
b1111111000000001 &
#2000
b11110000000011 !
b11110000000011 (
b1111110000000011 #
b1111110000000011 &
b11111111111111 $
b11111111111111 '
#3000
b11100000000101 !
b11100000000101 (
b1111100000000110 #
b1111100000000110 &
0%
#4000
b1011 !
b1011 (
b1111000000001100 #
b1111000000001100 &
b111111111111 $
b111111111111 '
#5000
b1111000000010111 !
b1111000000010111 (
0"
b1110000000011000 #
b1110000000011000 &
#6000
b1100010000110001 !
b1100010000110001 (
b1100000000110001 #
b1100000000110001 &
b1111111111 $
b1111111111 '
1%
#7000
b1000010001100011 !
b1000010001100011 (
b1000000001100011 #
b1000000001100011 &
#8000
b111000111 !
b111000111 (
b11000111 #
b11000111 &
b11111111 $
b11111111 '
#9000
b1010001101 !
b1010001101 (
b110001110 #
b110001110 &
0%
#10000
b1101011011 !
b1101011011 (
b1100011100 #
b1100011100 &
b111111 $
b111111 '
#11000
b11001110111 !
b11001110111 (
b11000111000 #
b11000111000 &
#12000
b110010000001 !
b110010000001 (
b110001110001 #
b110001110001 &
b1111 $
b1111 '
1%
#13000
b1100011110011 !
b1100011110011 (
b1100011100011 #
b1100011100011 &
#14000
b11000111001011 !
b11000111001011 (
b11000111000111 #
b11000111000111 &
b11 $
b11 '
#15000
b110001110010001 !
b110001110010001 (
b110001110001110 #
b110001110001110 &
0%
